ipserver/__init__.py
ipserver/__main__.py
ipserver/configs.py
ipserver/ipserver_cmd.py
ipserver/threads.py
ipserver/core/__init__.py
ipserver/core/object_factory.py
ipserver/core/pipeline.py
ipserver/keys/__init__.py
ipserver/keys/certificate.pem
ipserver/keys/private.pem
ipserver/server/__init__.py
ipserver/server/http_server.py
ipserver/server/http_server_module.py
ipserver/server/socket_server.py
ipserver/service/__init__.py
ipserver/service/args_builder.py
ipserver/service/dumpfile.py
ipserver/service/forwarding_socket.py
ipserver/service/view_helper.py
ipserver/util/__init__.py
ipserver/util/args_util.py
ipserver/util/data_io.py
ipserver/util/requester.py
ipserver/util/socket_client.py
ipserver/util/sys_util.py
ipserver/util/urlparser.py
ipserver-1.0.1.dist-info/licenses/LICENSE.md
ipserver-1.0.1.dist-info/METADATA
ipserver-1.0.1.dist-info/WHEEL
ipserver-1.0.1.dist-info/entry_points.txt
ipserver-1.0.1.dist-info/top_level.txt
ipserver-1.0.1.dist-info/RECORD
