Metadata-Version: 2.4
Name: ipserver
Version: 1.0.1
Summary: "ipserver" is a simple server that supports TCP, UDP, SSL, HTTP, and HTTPS protocols for various uses such as testing, debugging, or network investigation. It features also an interactive mode and forwarding capabilities. Additionally, you can customize its behavior using Python.
Home-page: https://github.com/deer-hunt/ipserver
Author: deer-hunt
License: MIT
Project-URL: Documentation, https://deer-hunt.github.io/ipserver/
Project-URL: Github, https://github.com/deer-hunt/ipserver/
Project-URL: Changelog, https://github.com/deer-hunt/ipserver/blob/main/CHANGELOG.md
Keywords: webserver,server,http,tcp,udp,proxy,tunnel,forwarding,simple server,application server,api,network investigation,file,microservices,debug,test
Classifier: Development Status :: 5 - Production/Stable
Classifier: Intended Audience :: Developers
Classifier: Intended Audience :: System Administrators
Classifier: Intended Audience :: Information Technology
Classifier: Intended Audience :: Science/Research
Classifier: Intended Audience :: Telecommunications Industry
Classifier: Programming Language :: Python :: 3
Classifier: Programming Language :: Python :: 3.6
Classifier: Programming Language :: Python :: 3.7
Classifier: Programming Language :: Python :: 3.8
Classifier: Programming Language :: Python :: 3.9
Classifier: Programming Language :: Python :: 3.10
Classifier: Programming Language :: Python :: 3.11
Classifier: Programming Language :: Python :: 3.12
Classifier: Programming Language :: Python :: 3.13
Classifier: License :: OSI Approved :: MIT License
Classifier: Operating System :: OS Independent
Classifier: Topic :: Software Development :: Libraries :: Python Modules
Requires-Python: >=3.6
License-File: LICENSE.md
Requires-Dist: multipart; python_version >= "3.8"
Requires-Dist: multipart==0.2.2; python_version < "3.8"
Dynamic: license-file
